accounts/__init__.py
accounts/admin.py
accounts/apps.py
accounts/models.py
accounts/serializers.py
accounts/tests.py
accounts/urls.py
accounts/urlsapi.py
accounts/views.py
accounts/viewsapi.py
accounts/migrations/0001_initial.py
accounts/migrations/__init__.py
accounts/templates/accounts/login.html
accounts/templates/accounts/register.html
django_acc-0.0.3.dist-info/DESCRIPTION.rst
django_acc-0.0.3.dist-info/METADATA
django_acc-0.0.3.dist-info/RECORD
django_acc-0.0.3.dist-info/WHEEL
django_acc-0.0.3.dist-info/metadata.json
django_acc-0.0.3.dist-info/top_level.txt
